SQLiteImageHandler/SQLiteImageHandler.py
SQLiteImageHandler/__init__.py
SQLiteImageHandler/__main__.py
SQLiteImageHandler-0.1.0.dist-info/LICENSE.md
SQLiteImageHandler-0.1.0.dist-info/METADATA
SQLiteImageHandler-0.1.0.dist-info/WHEEL
SQLiteImageHandler-0.1.0.dist-info/top_level.txt
SQLiteImageHandler-0.1.0.dist-info/RECORD
